paicli/__init__.py
paicli/api.py
paicli/cmd.py
paicli/config.py
paicli/intereactive.py
paicli/jobs.py
paicli/main.py
paicli/ssh.py
paicli/utils.py
paicli-0.5.5.dist-info/LICENSE
paicli-0.5.5.dist-info/METADATA
paicli-0.5.5.dist-info/WHEEL
paicli-0.5.5.dist-info/entry_points.txt
paicli-0.5.5.dist-info/top_level.txt
paicli-0.5.5.dist-info/RECORD
