Metadata-Version: 2.1
Name: paicli
Version: 0.5.5
Summary: Client for PAI
Home-page: UNKNOWN
Author: Sotetsu KOYAMADA
Author-email: koyamada-s@sys.i.kyoto-u.ac.jp
License: MIT
Platform: UNKNOWN
Classifier: Programming Language :: Python :: 3.5
Classifier: Programming Language :: Python :: 3.6
Classifier: Programming Language :: Python :: 3.7
Classifier: License :: OSI Approved :: MIT License
Requires-Dist: requests
Requires-Dist: pyyaml
Requires-Dist: prompt-toolkit (==1.0.9)
Requires-Dist: prettytable
Requires-Dist: termcolor
Requires-Dist: colorama
Requires-Dist: click
